Metadata-Version: 2.1
Name: housing_library_5493
Version: 0.1
Summary: Sample code for coding practice
Author-email: Gayathri <gayathri.katta@tigeranalytics.com>
Project-URL: Homepage, https://github.com/GayathriKatta123/MLE-training
Keywords: housing,data training
Classifier: Programming Language :: Python :: 3
Requires-Python: >=3.11
Requires-Dist: numpy
Requires-Dist: pandas
Requires-Dist: scikit-learn
